{
  "appName": "Chain Info (example)",
  "slug": "example-chain-info",
  "appDescription": "A simple chain information application",
  "ignite": ">=28.3.0",
  "dependencies": {},
  "cosmosSDK": ">=0.50.4",
  "authors": [
    {
      "name": "Ehsan Saradar",
      "github": "Ehsan-saradar"
    },
    {
      "name": "Danilo Pantani",
      "github": "Pantani"
    }
  ],
  "repositoryUrl": "https://github.com/ignite/apps/examples/chain-info",
  "documentationUrl": "https://github.com/ignite/apps/blob/main/examples/chain-info/README.md",
  "license": {
    "name": "MIT",
    "url": "https://github.com/ignite/apps/blob/main/LICENSE"
  },
  "keywords": [
    "chain-info",
    "example",
    "cli",
    "cosmos-sdk",
    "ignite app"
  ],
  "supportedPlatforms": [
    "mac",
    "linux"
  ],
  "icon": "",
  "cover": ""
}